flatxml/__init__.py
flatxml/test/__init__.py
flatxml/test/flatxml_tests.py
flatxml-0.12.dist-info/DESCRIPTION.rst
flatxml-0.12.dist-info/METADATA
flatxml-0.12.dist-info/metadata.json
flatxml-0.12.dist-info/RECORD
flatxml-0.12.dist-info/top_level.txt
flatxml-0.12.dist-info/WHEEL
