Metadata-Version: 2.0
Name: flatxml
Version: 0.12
Summary: Transform XML blob, file, or OrderedDict to a flat CSV or dictionary.
Home-page: https://github.com/AbleEng/flatxml
Author: Carlos Eduardo Rivera
Author-email: carlos@hiable.com
License: UNKNOWN
Download-URL: https://github.com/AbleEng/flatxml
Keywords: flat xml csv
Platform: UNKNOWN
Requires-Dist: xmltodict
